decode_7seg_anode/7seg_anode.v
module sev7seg_anode(
    input wire [3:0] digit,
    output reg [6:0] seg
);
always @(digit) begin
    case(digit)
        4'h0: seg = 7'h01;
        4'h1: seg = 7'h4F;
        4'h2: seg = 7'h12;
        4'h3: seg = 7'h06;
        4'h4: seg = 7'h4C;
        4'h5: seg = 7'h24;
        4'h6: seg = 7'h20;
        4'h7: seg = 7'h0F;
        4'h8: seg = 7'h00;
        4'h9: seg = 7'h0C;
        4'hA: seg = 7'h08;
        4'hB: seg = 7'h60;
        4'hC: seg = 7'h31;
        4'hD: seg = 7'h42;
        4'hE: seg = 7'h30;
        4'hF: seg = 7'h38;
        default: seg = 7'h7F;
    endcase
end
endmodule

decode_7seg_anode/7seg_anode_tb.v
module sev7seg_anode_tb;
    reg [3:0] digit;
    wire [6:0] seg;
    sev7seg_anode uut(digit, seg);
    reg [3:0] hex_digits [0:15];
    integer i;
    initial begin
        hex_digits[0] = 4'h0;
        hex_digits[1] = 4'h1;
        hex_digits[2] = 4'h2;
        hex_digits[3] = 4'h3;
        hex_digits[4] = 4'h4;
        hex_digits[5] = 4'h5;
        hex_digits[6] = 4'h6;
        hex_digits[7] = 4'h7;
        hex_digits[8] = 4'h8;
        hex_digits[9] = 4'h9;
        hex_digits[10] = 4'hA;
        hex_digits[11] = 4'hB;
        hex_digits[12] = 4'hC;
        hex_digits[13] = 4'hD;
        hex_digits[14] = 4'hE;
        hex_digits[15] = 4'hF;
    end

    task test_digit;
        begin
            digit = 4'h0; #5;
            for(i = 0 ; i < 16; i = i + 1) begin
                digit = hex_digits[i]; #5;
            end
        end
    endtask

    initial begin
        $dumpfile("wave_7seg_anode.vcd");
        $dumpvars(0, sev7seg_anode_tb);
        $monitor("Time: %0t, digit: %b, seg: %b", $time, digit, seg);
        test_digit();
        $finish;
    end
endmodule

decode_7seg_anode/wave_7seg_anode.vcd
$date
	Thu Jun 12 11:04:31 2025
$end
$version
	Icarus Verilog
$end
$timescale
	1s
$end
$scope module sev7seg_anode_tb $end
$var wire 7 ! seg [6:0] $end
$var reg 4 " digit [3:0] $end
$var integer 32 # i [31:0] $end
$scope module uut $end
$var wire 4 $ digit [3:0] $end
$var reg 7 % seg [6:0] $end
$upscope $end
$scope task test_digit $end
$upscope $end
$upscope $end
$enddefinitions $end
$comment Show the parameter values. $end
$dumpall
$end
#0
$dumpvars
b1 %
b0 $
bx #
b0 "
b1 !
$end
#5
b0 #
#10
b1001111 !
b1001111 %
b1 "
b1 $
b1 #
#15
b10010 !
b10010 %
b10 "
b10 $
b10 #
#20
b110 !
b110 %
b11 "
b11 $
b11 #
#25
b1001100 !
b1001100 %
b100 "
b100 $
b100 #
#30
b100100 !
b100100 %
b101 "
b101 $
b101 #
#35
b100000 !
b100000 %
b110 "
b110 $
b110 #
#40
b1111 !
b1111 %
b111 "
b111 $
b111 #
#45
b0 !
b0 %
b1000 "
b1000 $
b1000 #
#50
b1100 !
b1100 %
b1001 "
b1001 $
b1001 #
#55
b1000 !
b1000 %
b1010 "
b1010 $
b1010 #
#60
b1100000 !
b1100000 %
b1011 "
b1011 $
b1011 #
#65
b110001 !
b110001 %
b1100 "
b1100 $
b1100 #
#70
b1000010 !
b1000010 %
b1101 "
b1101 $
b1101 #
#75
b110000 !
b110000 %
b1110 "
b1110 $
b1110 #
#80
b111000 !
b111000 %
b1111 "
b1111 $
b1111 #
#85
b10000 #
