mux_4bit_4to1/mux41_4_tb.v
module mux41_1_tb;
    reg [3:0] in1, in2, in3, in4;
    reg [1:0] sel;
    wire [3:0] out;

    task init_val_test;
        begin
            in1 = 4'b1010; in2 = 4'b0101; in3 = 4'b1100; in4 = 4'b0011;
            sel = 2'b00; #5;
            sel = 2'b01; #5;
            sel = 2'b10; #5;
            sel = 2'b11; #5;

            in1 = 4'b1111; in2 = 4'b0000; in3 = 4'b1110; in4 = 4'b0001;
            sel = 2'b00; #5;
            sel = 2'b01; #5;
            sel = 2'b10; #5;
            sel = 2'b11; #5;
        end
    endtask

    mux41_1 m_tb(in1, in2, in3, in4, sel, out);
    initial begin
        $dumpfile("wave_mux41_1.vcd");
        $dumpvars(0, mux41_1_tb);
        $monitor("sel: %b, in1: %b, in2: %b, in3: %b, in4: %b, out: %b", sel, in1, in2, in3, in4, out);
        init_val_test();
        $finish;
    end

endmodule

mux_4bit_4to1/wave_mux41_1.vcd
$date
	Wed Jun 11 18:29:37 2025
$end
$version
	Icarus Verilog
$end
$timescale
	1s
$end
$scope module mux41_1_tb $end
$var wire 4 ! out [3:0] $end
$var reg 4 " in1 [3:0] $end
$var reg 4 # in2 [3:0] $end
$var reg 4 $ in3 [3:0] $end
$var reg 4 % in4 [3:0] $end
$var reg 2 & sel [1:0] $end
$scope module m_tb $end
$var wire 4 ' in1 [3:0] $end
$var wire 4 ( in2 [3:0] $end
$var wire 4 ) in3 [3:0] $end
$var wire 4 * in4 [3:0] $end
$var wire 2 + sel [1:0] $end
$var reg 4 , out [3:0] $end
$upscope $end
$scope task init_val_test $end
$upscope $end
$upscope $end
$enddefinitions $end
$comment Show the parameter values. $end
$dumpall
$end
#0
$dumpvars
b1010 ,
b0 +
b11 *
b1100 )
b101 (
b1010 '
b0 &
b11 %
b1100 $
b101 #
b1010 "
b1010 !
$end
#5
b101 !
b101 ,
b1 &
b1 +
#10
b1100 !
b1100 ,
b10 &
b10 +
#15
b11 !
b11 ,
b11 &
b11 +
#20
b1111 !
b1111 ,
b0 &
b0 +
b1 %
b1 *
b1110 $
b1110 )
b0 #
b0 (
b1111 "
b1111 '
#25
b0 !
b0 ,
b1 &
b1 +
#30
b1110 !
b1110 ,
b10 &
b10 +
#35
b1 !
b1 ,
b11 &
b11 +
