binary_decoder_2to4/bin_decoder.v
module bin_decoder(
    input a, b,
    output reg o0, o1, o2, o3
);
always @(*) begin
    case({a, b})
        2'b00: {o0, o1, o2, o3} = 4'b1000;
        2'b01: {o0, o1, o2, o3} = 4'b0100;
        2'b10: {o0, o1, o2, o3} = 4'b0010;
        2'b11: {o0, o1, o2, o3} = 4'b0001;
        default: {o0, o1, o2, o3} = {4{1'bx}}; 
    endcase
end
endmodule

binary_decoder_2to4/bin_decoder_tb.v
module bin_decoder_tb;
    reg a, b;
    wire o0, o1, o2, o3;

    bin_decoder bin_d_tb(a, b, o0, o1, o2, o3);
    task init_val_test;
        begin
            a = 0; b = 0; #5; 
            a = 0; b = 1; #5; 
            a = 1; b = 0; #5; 
            a = 1; b = 1; #5; 

            a = 0; b = 0; #5; 
            a = 0; b = 1; #5; 
            a = 1; b = 0; #5; 
            a = 1; b = 1; #5; 
        end
    endtask

    initial begin
        $dumpfile("wave_bin_decoder_tb.vcd");
        $dumpvars(0, bin_decoder_tb);
        $monitor("a: %b, b: %b, o0: %b, o1: %b, o2: %b, o3: %b", a, b, o0, o1, o2, o3); 
        init_val_test();
        $finish;
    end

endmodule

binary_decoder_2to4/wave_bin_decoder_tb.vcd
$date
	Wed Jun 11 18:47:10 2025
$end
$version
	Icarus Verilog
$end
$timescale
	1s
$end
$scope module bin_decoder_tb $end
$var wire 1 ! o3 $end
$var wire 1 " o2 $end
$var wire 1 # o1 $end
$var wire 1 $ o0 $end
$var reg 1 % a $end
$var reg 1 & b $end
$scope module bin_d_tb $end
$var wire 1 % a $end
$var wire 1 & b $end
$var reg 1 $ o0 $end
$var reg 1 # o1 $end
$var reg 1 " o2 $end
$var reg 1 ! o3 $end
$upscope $end
$scope task init_val_test $end
$upscope $end
$upscope $end
$enddefinitions $end
$comment Show the parameter values. $end
$dumpall
$end
#0
$dumpvars
0&
0%
1$
0#
0"
0!
$end
#5
0$
1#
1&
#10
0#
1"
0&
1%
#15
0"
1!
1&
#20
1$
0!
0&
0%
#25
0$
1#
1&
#30
0#
1"
0&
1%
#35
0"
1!
1&
