priority_encoder_8to3/pri_enc_8to3.v
module pri_enc_8to3(
    input wire d0, d1, d2, d3,d4, d5, d6, d7,
    output reg q0, q1, q2
);
always @(*) begin
    case ({d7, d6, d5, d4, d3, d2, d1, d0})
        8'b00000001: {q2, q1, q0} = 3'd0;
        8'b0000001x: {q2, q1, q0} = 3'd1; 
        8'b000001xx: {q2, q1, q0} = 3'd2;
        8'b00001xxx: {q2, q1, q0} = 3'd3;
        8'b0001xxxx: {q2, q1, q0} = 3'd4;
        8'b001xxxxx: {q2, q1, q0} = 3'd5;
        8'b01xxxxxx: {q2, q1, q0} = 3'd6;
        8'b1xxxxxxx: {q2, q1, q0} = 3'd7;
    endcase
end
endmodule

priority_encoder_8to3/pri_enc_8to3_tb.v
module pri_enc_8to3_tb;
    reg d0, d1, d2, d3, d4, d5, d6, d7;
    wire q0, q1, q2;

    pri_enc_8to3 uut(d0, d1, d2, d3, d4, d5, d6, d7, q0, q1, q2);

    task init_inputs_test;
        begin
            d0 = 1; d1 = 0; d2 = 0; d3 = 0;
            d4 = 0; d5 = 0; d6 = 0; d7 = 0; #5;
            d0 = 1'bx; d1 = 1; d2 = 0; d3 = 0;
            d4 = 0; d5 = 0; d6 = 0; d7 = 0; #5;
            d0 = 1'bx; d1 = 1'bx; d2 = 1; d3 = 0;
            d4 = 0; d5 = 0; d6 = 0; d7 = 0; #5;
            d0 = 1'bx; d1 = 1'bx; d2 = 1'bx; d3 = 1;
            d4 = 0; d5 = 0; d6 = 0; d7 = 0; #5;
            d0 = 1'bx; d1 = 1'bx; d2 = 1'bx; d3 = 1'bx;
            d4 = 1; d5 = 0; d6 = 0; d7 = 0; #5;
            d0 = 1'bx; d1 = 1'bx; d2 = 1'bx; d3 = 1'bx;
            d4 = 1'bx; d5 = 1; d6 = 0; d7 = 0; #5;
            d0 = 1'bx; d1 = 1'bx; d2 = 1'bx; d3 = 1'bx;
            d4 = 1'bx; d5 = 1'bx; d6 = 1; d7 = 0; #5;
            d0 = 1'bx; d1 = 1'bx; d2 = 1'bx; d3 = 1'bx;
            d4 = 1'bx; d5 = 1'bx; d6 = 1'bx; d7 = 1; #5;
        end
    endtask

    initial begin
        $dumpfile("wave_pri_enc_8to3_tb.vcd");
        $dumpvars(0, pri_enc_8to3_tb);
        $monitor("d0=%b, d1=%b, d2=%b, d3=%b, d4=%b, d5=%b, d6=%b, d7=%b => q2=%b, q1=%b, q0=%b", 
                 d0, d1, d2, d3, d4, d5, d6, d7, q2, q1, q0);
        init_inputs_test();
        $finish;
    end

endmodule

priority_encoder_8to3/wave_pri_enc_8to3_tb.vcd
$date
	Wed Jun 11 19:49:11 2025
$end
$version
	Icarus Verilog
$end
$timescale
	1s
$end
$scope module pri_enc_8to3_tb $end
$var wire 1 ! q2 $end
$var wire 1 " q1 $end
$var wire 1 # q0 $end
$var reg 1 $ d0 $end
$var reg 1 % d1 $end
$var reg 1 & d2 $end
$var reg 1 ' d3 $end
$var reg 1 ( d4 $end
$var reg 1 ) d5 $end
$var reg 1 * d6 $end
$var reg 1 + d7 $end
$scope module uut $end
$var wire 1 $ d0 $end
$var wire 1 % d1 $end
$var wire 1 & d2 $end
$var wire 1 ' d3 $end
$var wire 1 ( d4 $end
$var wire 1 ) d5 $end
$var wire 1 * d6 $end
$var wire 1 + d7 $end
$var reg 1 # q0 $end
$var reg 1 " q1 $end
$var reg 1 ! q2 $end
$upscope $end
$scope task init_inputs_test $end
$upscope $end
$upscope $end
$enddefinitions $end
$comment Show the parameter values. $end
$dumpall
$end
#0
$dumpvars
0+
0*
0)
0(
0'
0&
0%
1$
0#
0"
0!
$end
#5
1#
1%
x$
#10
1"
0#
1&
x%
#15
1#
1'
x&
#20
1!
0"
0#
1(
x'
#25
1#
1)
x(
#30
1"
0#
1*
x)
#35
1#
1+
x*
