dff_and_mux/dff_and_mux.v
module dff_and_mux(
    input clk,
    input wire [7:0] d,
    input wire [1:0] sel,
    output [7:0] q
);
    wire [7:0] dff_o1, dff_o2, dff_o3;    
    my_dff8 dff1(clk, d, dff_o1);
    my_dff8 dff2(clk, dff_o1, dff_o2);
    my_dff8 dff3(clk, dff_o2, dff_o3);
    mux_8bit_4to1 mux(.d0(d), .d1(dff_o1), .d2(dff_o2), .d3(dff_o3), .sel(sel), .q(q));
endmodule

module my_dff8(
    input clk,
    input wire [7:0] d,
    output reg [7:0] q
);
    always @(posedge clk) begin
        q <= d;
    end
endmodule

module mux_8bit_4to1(
    input wire [7:0] d0,
    input wire [7:0] d1,
    input wire [7:0] d2,
    input wire [7:0] d3,
    input wire [1:0] sel,
    output reg [7:0] q
);
    always @(*) begin 
        case(sel)
        2'b00: q = d0;
        2'b01: q = d1;
        2'b10: q = d2;
        2'b11: q = d3;
        default: q = {8{1'bx}}; 
        endcase
    end
endmodule

dff_and_mux/dff_and_mux_tb.v
module dff_and_mux_tb;
    reg [7:0] d;
    reg [1:0] sel;
    reg clk;
    wire [7:0] q;
    integer i, j;

    dff_and_mux dut (
        .clk(clk),
        .d(d),
        .sel(sel),
        .q(q)
    );

    task test_datain;
        begin
            fork begin
                for (j = 0; j < 256; j = j + 1) begin
                    #5 clk = ~clk;
                    d = j;
                end
            end
            begin
                repeat (256) begin
                    sel = 2'b00; #5; 
                    sel = 2'b01; #5;
                    sel = 2'b10; #5;
                    sel = 2'b11; #5;
                end
            end
            join
        end
    endtask

    initial begin
        clk = 0;
        d = 8'h00;
        sel = 2'b00;
        $dumpfile("dff_and_mux_tb.vcd");
        $dumpvars(0, dff_and_mux_tb);
        $monitor("Time: %0t, d: %b, sel: %b, q: %b", $time, d, sel, q);
        test_datain();
        $finish;
    end

endmodule

dff_and_mux/dff_and_mux_tb.vcd
$date
	Thu Jun 12 12:36:49 2025
$end
$version
	Icarus Verilog
$end
$timescale
	1s
$end
$scope module dff_and_mux_tb $end
$var wire 8 ! q [7:0] $end
$var reg 1 " clk $end
$var reg 8 # d [7:0] $end
$var reg 2 $ sel [1:0] $end
$var integer 32 % j [31:0] $end
$scope module dut $end
$var wire 1 " clk $end
$var wire 8 & d [7:0] $end
$var wire 2 ' sel [1:0] $end
$var wire 8 ( q [7:0] $end
$var wire 8 ) dff_o3 [7:0] $end
$var wire 8 * dff_o2 [7:0] $end
$var wire 8 + dff_o1 [7:0] $end
$scope module dff1 $end
$var wire 1 " clk $end
$var wire 8 , d [7:0] $end
$var reg 8 - q [7:0] $end
$upscope $end
$scope module dff2 $end
$var wire 1 " clk $end
$var wire 8 . d [7:0] $end
$var reg 8 / q [7:0] $end
$upscope $end
$scope module dff3 $end
$var wire 1 " clk $end
$var wire 8 0 d [7:0] $end
$var reg 8 1 q [7:0] $end
$upscope $end
$scope module mux $end
$var wire 8 2 d0 [7:0] $end
$var wire 8 3 d1 [7:0] $end
$var wire 8 4 d2 [7:0] $end
$var wire 8 5 d3 [7:0] $end
$var wire 2 6 sel [1:0] $end
$var reg 8 7 q [7:0] $end
$upscope $end
$upscope $end
$scope task test_datain $end
$upscope $end
$upscope $end
$enddefinitions $end
$comment Show the parameter values. $end
$dumpall
$end
#0
$dumpvars
b0 7
b0 6
bx 5
bx 4
bx 3
b0 2
bx 1
bx 0
bx /
bx .
bx -
b0 ,
bx +
bx *
bx )
b0 (
b0 '
b0 &
b0 %
b0 $
b0 #
0"
b0 !
$end
#5
b0 +
b0 -
b0 .
b0 3
b0 !
b0 (
b0 7
b1 %
1"
b1 $
b1 '
b1 6
#10
bx !
bx (
bx 7
b10 %
b1 #
b1 &
b1 ,
b1 2
0"
b10 $
b10 '
b10 6
#15
b0 *
b0 /
b0 0
b0 4
b10 +
b10 -
b10 .
b10 3
b11 %
b10 #
b10 &
b10 ,
b10 2
1"
b11 $
b11 '
b11 6
#20
b11 !
b11 (
b11 7
b100 %
b11 #
b11 &
b11 ,
b11 2
0"
b0 $
b0 '
b0 6
#25
b100 +
b100 -
b100 .
b100 3
b10 *
b10 /
b10 0
b10 4
b0 )
b0 1
b0 5
b100 !
b100 (
b100 7
b101 %
b100 #
b100 &
b100 ,
b100 2
1"
b1 $
b1 '
b1 6
#30
b10 !
b10 (
b10 7
b110 %
b101 #
b101 &
b101 ,
b101 2
0"
b10 $
b10 '
b10 6
#35
b10 )
b10 1
b10 5
b100 *
b100 /
b100 0
b100 4
b110 +
b110 -
b110 .
b110 3
b10 !
b10 (
b10 7
b111 %
b110 #
b110 &
b110 ,
b110 2
1"
b11 $
b11 '
b11 6
#40
b111 !
b111 (
b111 7
b1000 %
b111 #
b111 &
b111 ,
b111 2
0"
b0 $
b0 '
b0 6
#45
b1000 +
b1000 -
b1000 .
b1000 3
b110 *
b110 /
b110 0
b110 4
b100 )
b100 1
b100 5
b1000 !
b1000 (
b1000 7
b1001 %
b1000 #
b1000 &
b1000 ,
b1000 2
1"
b1 $
b1 '
b1 6
#50
b110 !
b110 (
b110 7
b1010 %
b1001 #
b1001 &
b1001 ,
b1001 2
0"
b10 $
b10 '
b10 6
#55
b110 )
b110 1
b110 5
b1000 *
b1000 /
b1000 0
b1000 4
b1010 +
b1010 -
b1010 .
b1010 3
b110 !
b110 (
b110 7
b1011 %
b1010 #
b1010 &
b1010 ,
b1010 2
1"
b11 $
b11 '
b11 6
#60
b1011 !
b1011 (
b1011 7
b1100 %
b1011 #
b1011 &
b1011 ,
b1011 2
0"
b0 $
b0 '
b0 6
#65
b1100 +
b1100 -
b1100 .
b1100 3
b1010 *
b1010 /
b1010 0
b1010 4
b1000 )
b1000 1
b1000 5
b1100 !
b1100 (
b1100 7
b1101 %
b1100 #
b1100 &
b1100 ,
b1100 2
1"
b1 $
b1 '
b1 6
#70
b1010 !
b1010 (
b1010 7
b1110 %
b1101 #
b1101 &
b1101 ,
b1101 2
0"
b10 $
b10 '
b10 6
#75
b1010 )
b1010 1
b1010 5
b1100 *
b1100 /
b1100 0
b1100 4
b1110 +
b1110 -
b1110 .
b1110 3
b1010 !
b1010 (
b1010 7
b1111 %
b1110 #
b1110 &
b1110 ,
b1110 2
1"
b11 $
b11 '
b11 6
#80
b1111 !
b1111 (
b1111 7
b10000 %
b1111 #
b1111 &
b1111 ,
b1111 2
0"
b0 $
b0 '
b0 6
#85
b10000 +
b10000 -
b10000 .
b10000 3
b1110 *
b1110 /
b1110 0
b1110 4
b1100 )
b1100 1
b1100 5
b10000 !
b10000 (
b10000 7
b10001 %
b10000 #
b10000 &
b10000 ,
b10000 2
1"
b1 $
b1 '
b1 6
#90
b1110 !
b1110 (
b1110 7
b10010 %
b10001 #
b10001 &
b10001 ,
b10001 2
0"
b10 $
b10 '
b10 6
#95
b1110 )
b1110 1
b1110 5
b10000 *
b10000 /
b10000 0
b10000 4
b10010 +
b10010 -
b10010 .
b10010 3
b1110 !
b1110 (
b1110 7
b10011 %
b10010 #
b10010 &
b10010 ,
b10010 2
1"
b11 $
b11 '
b11 6
#100
b10011 !
b10011 (
b10011 7
b10100 %
b10011 #
b10011 &
b10011 ,
b10011 2
0"
b0 $
b0 '
b0 6
#105
b10100 +
b10100 -
b10100 .
b10100 3
b10010 *
b10010 /
b10010 0
b10010 4
b10000 )
b10000 1
b10000 5
b10100 !
b10100 (
b10100 7
b10101 %
b10100 #
b10100 &
b10100 ,
b10100 2
1"
b1 $
b1 '
b1 6
#110
b10010 !
b10010 (
b10010 7
b10110 %
b10101 #
b10101 &
b10101 ,
b10101 2
0"
b10 $
b10 '
b10 6
#115
b10010 )
b10010 1
b10010 5
b10100 *
b10100 /
b10100 0
b10100 4
b10110 +
b10110 -
b10110 .
b10110 3
b10010 !
b10010 (
b10010 7
b10111 %
b10110 #
b10110 &
b10110 ,
b10110 2
1"
b11 $
b11 '
b11 6
#120
b10111 !
b10111 (
b10111 7
b11000 %
b10111 #
b10111 &
b10111 ,
b10111 2
0"
b0 $
b0 '
b0 6
#125
b11000 +
b11000 -
b11000 .
b11000 3
b10110 *
b10110 /
b10110 0
b10110 4
b10100 )
b10100 1
b10100 5
b11000 !
b11000 (
b11000 7
b11001 %
b11000 #
b11000 &
b11000 ,
b11000 2
1"
b1 $
b1 '
b1 6
#130
b10110 !
b10110 (
b10110 7
b11010 %
b11001 #
b11001 &
b11001 ,
b11001 2
0"
b10 $
b10 '
b10 6
#135
b10110 )
b10110 1
b10110 5
b11000 *
b11000 /
b11000 0
b11000 4
b11010 +
b11010 -
b11010 .
b11010 3
b10110 !
b10110 (
b10110 7
b11011 %
b11010 #
b11010 &
b11010 ,
b11010 2
1"
b11 $
b11 '
b11 6
#140
b11011 !
b11011 (
b11011 7
b11100 %
b11011 #
b11011 &
b11011 ,
b11011 2
0"
b0 $
b0 '
b0 6
#145
b11100 +
b11100 -
b11100 .
b11100 3
b11010 *
b11010 /
b11010 0
b11010 4
b11000 )
b11000 1
b11000 5
b11100 !
b11100 (
b11100 7
b11101 %
b11100 #
b11100 &
b11100 ,
b11100 2
1"
b1 $
b1 '
b1 6
#150
b11010 !
b11010 (
b11010 7
b11110 %
b11101 #
b11101 &
b11101 ,
b11101 2
0"
b10 $
b10 '
b10 6
#155
b11010 )
b11010 1
b11010 5
b11100 *
b11100 /
b11100 0
b11100 4
b11110 +
b11110 -
b11110 .
b11110 3
b11010 !
b11010 (
b11010 7
b11111 %
b11110 #
b11110 &
b11110 ,
b11110 2
1"
b11 $
b11 '
b11 6
#160
b11111 !
b11111 (
b11111 7
b100000 %
b11111 #
b11111 &
b11111 ,
b11111 2
0"
b0 $
b0 '
b0 6
#165
b100000 +
b100000 -
b100000 .
b100000 3
b11110 *
b11110 /
b11110 0
b11110 4
b11100 )
b11100 1
b11100 5
b100000 !
b100000 (
b100000 7
b100001 %
b100000 #
b100000 &
b100000 ,
b100000 2
1"
b1 $
b1 '
b1 6
#170
b11110 !
b11110 (
b11110 7
b100010 %
b100001 #
b100001 &
b100001 ,
b100001 2
0"
b10 $
b10 '
b10 6
#175
b11110 )
b11110 1
b11110 5
b100000 *
b100000 /
b100000 0
b100000 4
b100010 +
b100010 -
b100010 .
b100010 3
b11110 !
b11110 (
b11110 7
b100011 %
b100010 #
b100010 &
b100010 ,
b100010 2
1"
b11 $
b11 '
b11 6
#180
b100011 !
b100011 (
b100011 7
b100100 %
b100011 #
b100011 &
b100011 ,
b100011 2
0"
b0 $
b0 '
b0 6
#185
b100100 +
b100100 -
b100100 .
b100100 3
b100010 *
b100010 /
b100010 0
b100010 4
b100000 )
b100000 1
b100000 5
b100100 !
b100100 (
b100100 7
b100101 %
b100100 #
b100100 &
b100100 ,
b100100 2
1"
b1 $
b1 '
b1 6
#190
b100010 !
b100010 (
b100010 7
b100110 %
b100101 #
b100101 &
b100101 ,
b100101 2
0"
b10 $
b10 '
b10 6
#195
b100010 )
b100010 1
b100010 5
b100100 *
b100100 /
b100100 0
b100100 4
b100110 +
b100110 -
b100110 .
b100110 3
b100010 !
b100010 (
b100010 7
b100111 %
b100110 #
b100110 &
b100110 ,
b100110 2
1"
b11 $
b11 '
b11 6
#200
b100111 !
b100111 (
b100111 7
b101000 %
b100111 #
b100111 &
b100111 ,
b100111 2
0"
b0 $
b0 '
b0 6
#205
b101000 +
b101000 -
b101000 .
b101000 3
b100110 *
b100110 /
b100110 0
b100110 4
b100100 )
b100100 1
b100100 5
b101000 !
b101000 (
b101000 7
b101001 %
b101000 #
b101000 &
b101000 ,
b101000 2
1"
b1 $
b1 '
b1 6
#210
b100110 !
b100110 (
b100110 7
b101010 %
b101001 #
b101001 &
b101001 ,
b101001 2
0"
b10 $
b10 '
b10 6
#215
b100110 )
b100110 1
b100110 5
b101000 *
b101000 /
b101000 0
b101000 4
b101010 +
b101010 -
b101010 .
b101010 3
b100110 !
b100110 (
b100110 7
b101011 %
b101010 #
b101010 &
b101010 ,
b101010 2
1"
b11 $
b11 '
b11 6
#220
b101011 !
b101011 (
b101011 7
b101100 %
b101011 #
b101011 &
b101011 ,
b101011 2
0"
b0 $
b0 '
b0 6
#225
b101100 +
b101100 -
b101100 .
b101100 3
b101010 *
b101010 /
b101010 0
b101010 4
b101000 )
b101000 1
b101000 5
b101100 !
b101100 (
b101100 7
b101101 %
b101100 #
b101100 &
b101100 ,
b101100 2
1"
b1 $
b1 '
b1 6
#230
b101010 !
b101010 (
b101010 7
b101110 %
b101101 #
b101101 &
b101101 ,
b101101 2
0"
b10 $
b10 '
b10 6
#235
b101010 )
b101010 1
b101010 5
b101100 *
b101100 /
b101100 0
b101100 4
b101110 +
b101110 -
b101110 .
b101110 3
b101010 !
b101010 (
b101010 7
b101111 %
b101110 #
b101110 &
b101110 ,
b101110 2
1"
b11 $
b11 '
b11 6
#240
b101111 !
b101111 (
b101111 7
b110000 %
b101111 #
b101111 &
b101111 ,
b101111 2
0"
b0 $
b0 '
b0 6
#245
b110000 +
b110000 -
b110000 .
b110000 3
b101110 *
b101110 /
b101110 0
b101110 4
b101100 )
b101100 1
b101100 5
b110000 !
b110000 (
b110000 7
b110001 %
b110000 #
b110000 &
b110000 ,
b110000 2
1"
b1 $
b1 '
b1 6
#250
b101110 !
b101110 (
b101110 7
b110010 %
b110001 #
b110001 &
b110001 ,
b110001 2
0"
b10 $
b10 '
b10 6
#255
b101110 )
b101110 1
b101110 5
b110000 *
b110000 /
b110000 0
b110000 4
b110010 +
b110010 -
b110010 .
b110010 3
b101110 !
b101110 (
b101110 7
b110011 %
b110010 #
b110010 &
b110010 ,
b110010 2
1"
b11 $
b11 '
b11 6
#260
b110011 !
b110011 (
b110011 7
b110100 %
b110011 #
b110011 &
b110011 ,
b110011 2
0"
b0 $
b0 '
b0 6
#265
b110100 +
b110100 -
b110100 .
b110100 3
b110010 *
b110010 /
b110010 0
b110010 4
b110000 )
b110000 1
b110000 5
b110100 !
b110100 (
b110100 7
b110101 %
b110100 #
b110100 &
b110100 ,
b110100 2
1"
b1 $
b1 '
b1 6
#270
b110010 !
b110010 (
b110010 7
b110110 %
b110101 #
b110101 &
b110101 ,
b110101 2
0"
b10 $
b10 '
b10 6
#275
b110010 )
b110010 1
b110010 5
b110100 *
b110100 /
b110100 0
b110100 4
b110110 +
b110110 -
b110110 .
b110110 3
b110010 !
b110010 (
b110010 7
b110111 %
b110110 #
b110110 &
b110110 ,
b110110 2
1"
b11 $
b11 '
b11 6
#280
b110111 !
b110111 (
b110111 7
b111000 %
b110111 #
b110111 &
b110111 ,
b110111 2
0"
b0 $
b0 '
b0 6
#285
b111000 +
b111000 -
b111000 .
b111000 3
b110110 *
b110110 /
b110110 0
b110110 4
b110100 )
b110100 1
b110100 5
b111000 !
b111000 (
b111000 7
b111001 %
b111000 #
b111000 &
b111000 ,
b111000 2
1"
b1 $
b1 '
b1 6
#290
b110110 !
b110110 (
b110110 7
b111010 %
b111001 #
b111001 &
b111001 ,
b111001 2
0"
b10 $
b10 '
b10 6
#295
b110110 )
b110110 1
b110110 5
b111000 *
b111000 /
b111000 0
b111000 4
b111010 +
b111010 -
b111010 .
b111010 3
b110110 !
b110110 (
b110110 7
b111011 %
b111010 #
b111010 &
b111010 ,
b111010 2
1"
b11 $
b11 '
b11 6
#300
b111011 !
b111011 (
b111011 7
b111100 %
b111011 #
b111011 &
b111011 ,
b111011 2
0"
b0 $
b0 '
b0 6
#305
b111100 +
b111100 -
b111100 .
b111100 3
b111010 *
b111010 /
b111010 0
b111010 4
b111000 )
b111000 1
b111000 5
b111100 !
b111100 (
b111100 7
b111101 %
b111100 #
b111100 &
b111100 ,
b111100 2
1"
b1 $
b1 '
b1 6
#310
b111010 !
b111010 (
b111010 7
b111110 %
b111101 #
b111101 &
b111101 ,
b111101 2
0"
b10 $
b10 '
b10 6
#315
b111010 )
b111010 1
b111010 5
b111100 *
b111100 /
b111100 0
b111100 4
b111110 +
b111110 -
b111110 .
b111110 3
b111010 !
b111010 (
b111010 7
b111111 %
b111110 #
b111110 &
b111110 ,
b111110 2
1"
b11 $
b11 '
b11 6
#320
b111111 !
b111111 (
b111111 7
b1000000 %
b111111 #
b111111 &
b111111 ,
b111111 2
0"
b0 $
b0 '
b0 6
#325
b1000000 +
b1000000 -
b1000000 .
b1000000 3
b111110 *
b111110 /
b111110 0
b111110 4
b111100 )
b111100 1
b111100 5
b1000000 !
b1000000 (
b1000000 7
b1000001 %
b1000000 #
b1000000 &
b1000000 ,
b1000000 2
1"
b1 $
b1 '
b1 6
#330
b111110 !
b111110 (
b111110 7
b1000010 %
b1000001 #
b1000001 &
b1000001 ,
b1000001 2
0"
b10 $
b10 '
b10 6
#335
b111110 )
b111110 1
b111110 5
b1000000 *
b1000000 /
b1000000 0
b1000000 4
b1000010 +
b1000010 -
b1000010 .
b1000010 3
b111110 !
b111110 (
b111110 7
b1000011 %
b1000010 #
b1000010 &
b1000010 ,
b1000010 2
1"
b11 $
b11 '
b11 6
#340
b1000011 !
b1000011 (
b1000011 7
b1000100 %
b1000011 #
b1000011 &
b1000011 ,
b1000011 2
0"
b0 $
b0 '
b0 6
#345
b1000100 +
b1000100 -
b1000100 .
b1000100 3
b1000010 *
b1000010 /
b1000010 0
b1000010 4
b1000000 )
b1000000 1
b1000000 5
b1000100 !
b1000100 (
b1000100 7
b1000101 %
b1000100 #
b1000100 &
b1000100 ,
b1000100 2
1"
b1 $
b1 '
b1 6
#350
b1000010 !
b1000010 (
b1000010 7
b1000110 %
b1000101 #
b1000101 &
b1000101 ,
b1000101 2
0"
b10 $
b10 '
b10 6
#355
b1000010 )
b1000010 1
b1000010 5
b1000100 *
b1000100 /
b1000100 0
b1000100 4
b1000110 +
b1000110 -
b1000110 .
b1000110 3
b1000010 !
b1000010 (
b1000010 7
b1000111 %
b1000110 #
b1000110 &
b1000110 ,
b1000110 2
1"
b11 $
b11 '
b11 6
#360
b1000111 !
b1000111 (
b1000111 7
b1001000 %
b1000111 #
b1000111 &
b1000111 ,
b1000111 2
0"
b0 $
b0 '
b0 6
#365
b1001000 +
b1001000 -
b1001000 .
b1001000 3
b1000110 *
b1000110 /
b1000110 0
b1000110 4
b1000100 )
b1000100 1
b1000100 5
b1001000 !
b1001000 (
b1001000 7
b1001001 %
b1001000 #
b1001000 &
b1001000 ,
b1001000 2
1"
b1 $
b1 '
b1 6
#370
b1000110 !
b1000110 (
b1000110 7
b1001010 %
b1001001 #
b1001001 &
b1001001 ,
b1001001 2
0"
b10 $
b10 '
b10 6
#375
b1000110 )
b1000110 1
b1000110 5
b1001000 *
b1001000 /
b1001000 0
b1001000 4
b1001010 +
b1001010 -
b1001010 .
b1001010 3
b1000110 !
b1000110 (
b1000110 7
b1001011 %
b1001010 #
b1001010 &
b1001010 ,
b1001010 2
1"
b11 $
b11 '
b11 6
#380
b1001011 !
b1001011 (
b1001011 7
b1001100 %
b1001011 #
b1001011 &
b1001011 ,
b1001011 2
0"
b0 $
b0 '
b0 6
#385
b1001100 +
b1001100 -
b1001100 .
b1001100 3
b1001010 *
b1001010 /
b1001010 0
b1001010 4
b1001000 )
b1001000 1
b1001000 5
b1001100 !
b1001100 (
b1001100 7
b1001101 %
b1001100 #
b1001100 &
b1001100 ,
b1001100 2
1"
b1 $
b1 '
b1 6
#390
b1001010 !
b1001010 (
b1001010 7
b1001110 %
b1001101 #
b1001101 &
b1001101 ,
b1001101 2
0"
b10 $
b10 '
b10 6
#395
b1001010 )
b1001010 1
b1001010 5
b1001100 *
b1001100 /
b1001100 0
b1001100 4
b1001110 +
b1001110 -
b1001110 .
b1001110 3
b1001010 !
b1001010 (
b1001010 7
b1001111 %
b1001110 #
b1001110 &
b1001110 ,
b1001110 2
1"
b11 $
b11 '
b11 6
#400
b1001111 !
b1001111 (
b1001111 7
b1010000 %
b1001111 #
b1001111 &
b1001111 ,
b1001111 2
0"
b0 $
b0 '
b0 6
#405
b1010000 +
b1010000 -
b1010000 .
b1010000 3
b1001110 *
b1001110 /
b1001110 0
b1001110 4
b1001100 )
b1001100 1
b1001100 5
b1010000 !
b1010000 (
b1010000 7
b1010001 %
b1010000 #
b1010000 &
b1010000 ,
b1010000 2
1"
b1 $
b1 '
b1 6
#410
b1001110 !
b1001110 (
b1001110 7
b1010010 %
b1010001 #
b1010001 &
b1010001 ,
b1010001 2
0"
b10 $
b10 '
b10 6
#415
b1001110 )
b1001110 1
b1001110 5
b1010000 *
b1010000 /
b1010000 0
b1010000 4
b1010010 +
b1010010 -
b1010010 .
b1010010 3
b1001110 !
b1001110 (
b1001110 7
b1010011 %
b1010010 #
b1010010 &
b1010010 ,
b1010010 2
1"
b11 $
b11 '
b11 6
#420
b1010011 !
b1010011 (
b1010011 7
b1010100 %
b1010011 #
b1010011 &
b1010011 ,
b1010011 2
0"
b0 $
b0 '
b0 6
#425
b1010100 +
b1010100 -
b1010100 .
b1010100 3
b1010010 *
b1010010 /
b1010010 0
b1010010 4
b1010000 )
b1010000 1
b1010000 5
b1010100 !
b1010100 (
b1010100 7
b1010101 %
b1010100 #
b1010100 &
b1010100 ,
b1010100 2
1"
b1 $
b1 '
b1 6
#430
b1010010 !
b1010010 (
b1010010 7
b1010110 %
b1010101 #
b1010101 &
b1010101 ,
b1010101 2
0"
b10 $
b10 '
b10 6
#435
b1010010 )
b1010010 1
b1010010 5
b1010100 *
b1010100 /
b1010100 0
b1010100 4
b1010110 +
b1010110 -
b1010110 .
b1010110 3
b1010010 !
b1010010 (
b1010010 7
b1010111 %
b1010110 #
b1010110 &
b1010110 ,
b1010110 2
1"
b11 $
b11 '
b11 6
#440
b1010111 !
b1010111 (
b1010111 7
b1011000 %
b1010111 #
b1010111 &
b1010111 ,
b1010111 2
0"
b0 $
b0 '
b0 6
#445
b1011000 +
b1011000 -
b1011000 .
b1011000 3
b1010110 *
b1010110 /
b1010110 0
b1010110 4
b1010100 )
b1010100 1
b1010100 5
b1011000 !
b1011000 (
b1011000 7
b1011001 %
b1011000 #
b1011000 &
b1011000 ,
b1011000 2
1"
b1 $
b1 '
b1 6
#450
b1010110 !
b1010110 (
b1010110 7
b1011010 %
b1011001 #
b1011001 &
b1011001 ,
b1011001 2
0"
b10 $
b10 '
b10 6
#455
b1010110 )
b1010110 1
b1010110 5
b1011000 *
b1011000 /
b1011000 0
b1011000 4
b1011010 +
b1011010 -
b1011010 .
b1011010 3
b1010110 !
b1010110 (
b1010110 7
b1011011 %
b1011010 #
b1011010 &
b1011010 ,
b1011010 2
1"
b11 $
b11 '
b11 6
#460
b1011011 !
b1011011 (
b1011011 7
b1011100 %
b1011011 #
b1011011 &
b1011011 ,
b1011011 2
0"
b0 $
b0 '
b0 6
#465
b1011100 +
b1011100 -
b1011100 .
b1011100 3
b1011010 *
b1011010 /
b1011010 0
b1011010 4
b1011000 )
b1011000 1
b1011000 5
b1011100 !
b1011100 (
b1011100 7
b1011101 %
b1011100 #
b1011100 &
b1011100 ,
b1011100 2
1"
b1 $
b1 '
b1 6
#470
b1011010 !
b1011010 (
b1011010 7
b1011110 %
b1011101 #
b1011101 &
b1011101 ,
b1011101 2
0"
b10 $
b10 '
b10 6
#475
b1011010 )
b1011010 1
b1011010 5
b1011100 *
b1011100 /
b1011100 0
b1011100 4
b1011110 +
b1011110 -
b1011110 .
b1011110 3
b1011010 !
b1011010 (
b1011010 7
b1011111 %
b1011110 #
b1011110 &
b1011110 ,
b1011110 2
1"
b11 $
b11 '
b11 6
#480
b1011111 !
b1011111 (
b1011111 7
b1100000 %
b1011111 #
b1011111 &
b1011111 ,
b1011111 2
0"
b0 $
b0 '
b0 6
#485
b1100000 +
b1100000 -
b1100000 .
b1100000 3
b1011110 *
b1011110 /
b1011110 0
b1011110 4
b1011100 )
b1011100 1
b1011100 5
b1100000 !
b1100000 (
b1100000 7
b1100001 %
b1100000 #
b1100000 &
b1100000 ,
b1100000 2
1"
b1 $
b1 '
b1 6
#490
b1011110 !
b1011110 (
b1011110 7
b1100010 %
b1100001 #
b1100001 &
b1100001 ,
b1100001 2
0"
b10 $
b10 '
b10 6
#495
b1011110 )
b1011110 1
b1011110 5
b1100000 *
b1100000 /
b1100000 0
b1100000 4
b1100010 +
b1100010 -
b1100010 .
b1100010 3
b1011110 !
b1011110 (
b1011110 7
b1100011 %
b1100010 #
b1100010 &
b1100010 ,
b1100010 2
1"
b11 $
b11 '
b11 6
#500
b1100011 !
b1100011 (
b1100011 7
b1100100 %
b1100011 #
b1100011 &
b1100011 ,
b1100011 2
0"
b0 $
b0 '
b0 6
#505
b1100100 +
b1100100 -
b1100100 .
b1100100 3
b1100010 *
b1100010 /
b1100010 0
b1100010 4
b1100000 )
b1100000 1
b1100000 5
b1100100 !
b1100100 (
b1100100 7
b1100101 %
b1100100 #
b1100100 &
b1100100 ,
b1100100 2
1"
b1 $
b1 '
b1 6
#510
b1100010 !
b1100010 (
b1100010 7
b1100110 %
b1100101 #
b1100101 &
b1100101 ,
b1100101 2
0"
b10 $
b10 '
b10 6
#515
b1100010 )
b1100010 1
b1100010 5
b1100100 *
b1100100 /
b1100100 0
b1100100 4
b1100110 +
b1100110 -
b1100110 .
b1100110 3
b1100010 !
b1100010 (
b1100010 7
b1100111 %
b1100110 #
b1100110 &
b1100110 ,
b1100110 2
1"
b11 $
b11 '
b11 6
#520
b1100111 !
b1100111 (
b1100111 7
b1101000 %
b1100111 #
b1100111 &
b1100111 ,
b1100111 2
0"
b0 $
b0 '
b0 6
#525
b1101000 +
b1101000 -
b1101000 .
b1101000 3
b1100110 *
b1100110 /
b1100110 0
b1100110 4
b1100100 )
b1100100 1
b1100100 5
b1101000 !
b1101000 (
b1101000 7
b1101001 %
b1101000 #
b1101000 &
b1101000 ,
b1101000 2
1"
b1 $
b1 '
b1 6
#530
b1100110 !
b1100110 (
b1100110 7
b1101010 %
b1101001 #
b1101001 &
b1101001 ,
b1101001 2
0"
b10 $
b10 '
b10 6
#535
b1100110 )
b1100110 1
b1100110 5
b1101000 *
b1101000 /
b1101000 0
b1101000 4
b1101010 +
b1101010 -
b1101010 .
b1101010 3
b1100110 !
b1100110 (
b1100110 7
b1101011 %
b1101010 #
b1101010 &
b1101010 ,
b1101010 2
1"
b11 $
b11 '
b11 6
#540
b1101011 !
b1101011 (
b1101011 7
b1101100 %
b1101011 #
b1101011 &
b1101011 ,
b1101011 2
0"
b0 $
b0 '
b0 6
#545
b1101100 +
b1101100 -
b1101100 .
b1101100 3
b1101010 *
b1101010 /
b1101010 0
b1101010 4
b1101000 )
b1101000 1
b1101000 5
b1101100 !
b1101100 (
b1101100 7
b1101101 %
b1101100 #
b1101100 &
b1101100 ,
b1101100 2
1"
b1 $
b1 '
b1 6
#550
b1101010 !
b1101010 (
b1101010 7
b1101110 %
b1101101 #
b1101101 &
b1101101 ,
b1101101 2
0"
b10 $
b10 '
b10 6
#555
b1101010 )
b1101010 1
b1101010 5
b1101100 *
b1101100 /
b1101100 0
b1101100 4
b1101110 +
b1101110 -
b1101110 .
b1101110 3
b1101010 !
b1101010 (
b1101010 7
b1101111 %
b1101110 #
b1101110 &
b1101110 ,
b1101110 2
1"
b11 $
b11 '
b11 6
#560
b1101111 !
b1101111 (
b1101111 7
b1110000 %
b1101111 #
b1101111 &
b1101111 ,
b1101111 2
0"
b0 $
b0 '
b0 6
#565
b1110000 +
b1110000 -
b1110000 .
b1110000 3
b1101110 *
b1101110 /
b1101110 0
b1101110 4
b1101100 )
b1101100 1
b1101100 5
b1110000 !
b1110000 (
b1110000 7
b1110001 %
b1110000 #
b1110000 &
b1110000 ,
b1110000 2
1"
b1 $
b1 '
b1 6
#570
b1101110 !
b1101110 (
b1101110 7
b1110010 %
b1110001 #
b1110001 &
b1110001 ,
b1110001 2
0"
b10 $
b10 '
b10 6
#575
b1101110 )
b1101110 1
b1101110 5
b1110000 *
b1110000 /
b1110000 0
b1110000 4
b1110010 +
b1110010 -
b1110010 .
b1110010 3
b1101110 !
b1101110 (
b1101110 7
b1110011 %
b1110010 #
b1110010 &
b1110010 ,
b1110010 2
1"
b11 $
b11 '
b11 6
#580
b1110011 !
b1110011 (
b1110011 7
b1110100 %
b1110011 #
b1110011 &
b1110011 ,
b1110011 2
0"
b0 $
b0 '
b0 6
#585
b1110100 +
b1110100 -
b1110100 .
b1110100 3
b1110010 *
b1110010 /
b1110010 0
b1110010 4
b1110000 )
b1110000 1
b1110000 5
b1110100 !
b1110100 (
b1110100 7
b1110101 %
b1110100 #
b1110100 &
b1110100 ,
b1110100 2
1"
b1 $
b1 '
b1 6
#590
b1110010 !
b1110010 (
b1110010 7
b1110110 %
b1110101 #
b1110101 &
b1110101 ,
b1110101 2
0"
b10 $
b10 '
b10 6
#595
b1110010 )
b1110010 1
b1110010 5
b1110100 *
b1110100 /
b1110100 0
b1110100 4
b1110110 +
b1110110 -
b1110110 .
b1110110 3
b1110010 !
b1110010 (
b1110010 7
b1110111 %
b1110110 #
b1110110 &
b1110110 ,
b1110110 2
1"
b11 $
b11 '
b11 6
#600
b1110111 !
b1110111 (
b1110111 7
b1111000 %
b1110111 #
b1110111 &
b1110111 ,
b1110111 2
0"
b0 $
b0 '
b0 6
#605
b1111000 +
b1111000 -
b1111000 .
b1111000 3
b1110110 *
b1110110 /
b1110110 0
b1110110 4
b1110100 )
b1110100 1
b1110100 5
b1111000 !
b1111000 (
b1111000 7
b1111001 %
b1111000 #
b1111000 &
b1111000 ,
b1111000 2
1"
b1 $
b1 '
b1 6
#610
b1110110 !
b1110110 (
b1110110 7
b1111010 %
b1111001 #
b1111001 &
b1111001 ,
b1111001 2
0"
b10 $
b10 '
b10 6
